msgsplitter/__init__.py
msgsplitter/_split_message.py
msgsplitter/exceptions.py
msgsplitter/split.py
msgsplitter/formatters/__init__.py
msgsplitter/formatters/formatter_base.py
msgsplitter/formatters/indicator_formatter.py
msgsplitter/tests/__init__.py
msgsplitter/tests/test_split.py
msgsplitter-1.0.dist-info/LICENSE
msgsplitter-1.0.dist-info/METADATA
msgsplitter-1.0.dist-info/WHEEL
msgsplitter-1.0.dist-info/top_level.txt
msgsplitter-1.0.dist-info/RECORD
