Metadata-Version: 2.1
Name: msgsplitter
Version: 1.0
Summary: Split messages (strings) to fit an arbitrary character limit
Home-page: https://github.com/Elijas/msgsplitter
Author: Elijas Dapšauskas
Author-email: master.elijas@gmail.com
License: UNKNOWN
Platform: Any
Classifier: Programming Language :: Python :: 3.7
Classifier: Programming Language :: Python :: 3.8
Classifier: License :: OSI Approved :: MIT License
Classifier: Operating System :: OS Independent
